setup.py
pyramid_asbool/__init__.py
pyramid_asbool.egg-info/PKG-INFO
pyramid_asbool.egg-info/SOURCES.txt
pyramid_asbool.egg-info/dependency_links.txt
pyramid_asbool.egg-info/not-zip-safe
pyramid_asbool.egg-info/requires.txt
pyramid_asbool.egg-info/top_level.txt