Metadata-Version: 1.1
Name: pyramid-asbool
Version: 0.0.2
Summary: Extension to support extra truthy items
Home-page: https://github.com/sontek/pyramid_asbool
Author: John Anderson
Author-email: sontek@gmail.com
License: BSD
Keywords: pyramid
Platform: UNKNOWN
Classifier: Intended Audience :: Developers
Classifier: License :: OSI Approved :: BSD License
Classifier: Operating System :: OS Independent
Classifier: Programming Language :: Python
Classifier: Topic :: Internet :: WWW/HTTP :: Dynamic Content
Classifier: Topic :: Software Development :: Libraries :: Python Modules
